odoo/addons/mrp_subcontracting_bom_dual_use/README.rst
odoo/addons/mrp_subcontracting_bom_dual_use/__init__.py
odoo/addons/mrp_subcontracting_bom_dual_use/__manifest__.py
odoo/addons/mrp_subcontracting_bom_dual_use/i18n/es.po
odoo/addons/mrp_subcontracting_bom_dual_use/i18n/it.po
odoo/addons/mrp_subcontracting_bom_dual_use/i18n/mrp_subcontracting_bom_dual_use.pot
odoo/addons/mrp_subcontracting_bom_dual_use/models/__init__.py
odoo/addons/mrp_subcontracting_bom_dual_use/models/mrp_bom.py
odoo/addons/mrp_subcontracting_bom_dual_use/models/mrp_production.py
odoo/addons/mrp_subcontracting_bom_dual_use/readme/CONTRIBUTORS.md
odoo/addons/mrp_subcontracting_bom_dual_use/readme/DESCRIPTION.md
odoo/addons/mrp_subcontracting_bom_dual_use/readme/USAGE.md
odoo/addons/mrp_subcontracting_bom_dual_use/static/description/icon.png
odoo/addons/mrp_subcontracting_bom_dual_use/static/description/index.html
odoo/addons/mrp_subcontracting_bom_dual_use/tests/__init__.py
odoo/addons/mrp_subcontracting_bom_dual_use/tests/test_mrp_subcontracting_bom_dual_use.py
odoo/addons/mrp_subcontracting_bom_dual_use/views/mrp_bom_view.xml
odoo_addon_mrp_subcontracting_bom_dual_use-17.0.1.0.1.dist-info/METADATA
odoo_addon_mrp_subcontracting_bom_dual_use-17.0.1.0.1.dist-info/WHEEL
odoo_addon_mrp_subcontracting_bom_dual_use-17.0.1.0.1.dist-info/top_level.txt
odoo_addon_mrp_subcontracting_bom_dual_use-17.0.1.0.1.dist-info/RECORD
